commandtaker/__init__.py
commandtaker/cmndtkr.py
commandtaker-1.1.8.dist-info/LICENSE
commandtaker-1.1.8.dist-info/METADATA
commandtaker-1.1.8.dist-info/WHEEL
commandtaker-1.1.8.dist-info/top_level.txt
commandtaker-1.1.8.dist-info/RECORD
